dataclass_property/__init__.py
dataclass_property/__meta__.py
dataclass_property/datetime_utils.py
dataclass_property/field_prop.py
dataclass_property/interface.py
dataclass_property/internals.py
dataclass_property/internals_310.py
dataclass_property/internals_old.py
dataclass_property/weekdays_list.py
dataclass_property/__pycache__/__init__.cpython-310.pyc
dataclass_property/__pycache__/__init__.cpython-38.pyc
dataclass_property/__pycache__/__meta__.cpython-310.pyc
dataclass_property/__pycache__/__meta__.cpython-38.pyc
dataclass_property/__pycache__/datetime_utils.cpython-38.pyc
dataclass_property/__pycache__/field_prop.cpython-310.pyc
dataclass_property/__pycache__/field_prop.cpython-38.pyc
dataclass_property/__pycache__/interface.cpython-310.pyc
dataclass_property/__pycache__/interface.cpython-38.pyc
dataclass_property/__pycache__/internals.cpython-38.pyc
dataclass_property/__pycache__/internals_310.cpython-310.pyc
dataclass_property/__pycache__/internals_old.cpython-310.pyc
dataclass_property/__pycache__/internals_old.cpython-38.pyc
dataclass_property/__pycache__/weekdays_list.cpython-38.pyc
dataclass_property-1.4.1.dist-info/LICENSE
dataclass_property-1.4.1.dist-info/METADATA
dataclass_property-1.4.1.dist-info/WHEEL
dataclass_property-1.4.1.dist-info/top_level.txt
dataclass_property-1.4.1.dist-info/RECORD
