Metadata-Version: 2.1
Name: dataclass-property
Version: 1.4.1
Summary: Add the ability to use properties with dataclasses.
Home-page: https://github.com/justengel/dataclass_property
Author: Justin Engel
Author-email: jtengel08@gmail.com
License: MIT
Download-URL: https://github.com/justengel/dataclass_property/archive/v1.4.1.tar.gz
Keywords: dataclasses dataclass property field_property
Platform: any
Classifier: Programming Language :: Python
Classifier: Programming Language :: Python :: 3
Classifier: Operating System :: OS Independent
License-File: LICENSE
